storagebox/__init__.py
storagebox/api.py
storagebox/repository/__init__.py
storagebox/repository/deduplication.py
storagebox/repository/dynamodb.py
storagebox/repository/item_bank.py
storagebox/settings.py
storagebox-1.0.7.dist-info/LICENSE
storagebox-1.0.7.dist-info/WHEEL
storagebox-1.0.7.dist-info/METADATA
storagebox-1.0.7.dist-info/RECORD
