Metadata-Version: 2.1
Name: storagebox
Version: 1.0.7
Summary: A reusable, idempotent, and exactly once deduplication API
Home-page: https://github.com/peter-emil/StorageBox
Author: Peter Emil Halim
Author-email: peter@peteremil.com
Requires-Python: >=3.8,<4.0
Classifier: Programming Language :: Python :: 3
Classifier: Programming Language :: Python :: 3.8
Requires-Dist: boto3 (>=1.16.63,<2.0.0)
